smb_zfs/__init__.py
smb_zfs/cli.py
smb_zfs/config_generator.py
smb_zfs/const.py
smb_zfs/errors.py
smb_zfs/smb_zfs.py
smb_zfs/smb_zfs_wizard.py
smb_zfs/state_manager.py
smb_zfs/system.py
smb_zfs/utils.py
smb_zfs/zfs.py
smb_zfs-0.8.0.dist-info/METADATA
smb_zfs-0.8.0.dist-info/WHEEL
smb_zfs-0.8.0.dist-info/entry_points.txt
smb_zfs-0.8.0.dist-info/top_level.txt
smb_zfs-0.8.0.dist-info/RECORD
