Metadata-Version: 2.4
Name: smb-zfs
Version: 0.8.0
Summary: A tool to manage Samba on a ZFS-backed system.
Author-email: Nils Stein <github.nstein@mailbox.org>
Project-URL: Homepage, https://github.com/mietzen/smb-zfs
Project-URL: Issues, https://github.com/mietzen/smb-zfs/issues
Keywords: zfs,samba,debian
Classifier: Development Status :: 4 - Beta
Classifier: Programming Language :: Python :: 3
Classifier: Operating System :: POSIX :: Linux
Requires-Python: >=3.10
